odoo/addons/project_timesheet_time_control_sale/README.rst
odoo/addons/project_timesheet_time_control_sale/__init__.py
odoo/addons/project_timesheet_time_control_sale/__manifest__.py
odoo/addons/project_timesheet_time_control_sale/i18n/it.po
odoo/addons/project_timesheet_time_control_sale/i18n/project_timesheet_time_control_sale.pot
odoo/addons/project_timesheet_time_control_sale/models/__init__.py
odoo/addons/project_timesheet_time_control_sale/models/account_invoice.py
odoo/addons/project_timesheet_time_control_sale/readme/CONTRIBUTORS.rst
odoo/addons/project_timesheet_time_control_sale/readme/DESCRIPTION.rst
odoo/addons/project_timesheet_time_control_sale/static/description/icon.png
odoo/addons/project_timesheet_time_control_sale/static/description/index.html
odoo12_addon_project_timesheet_time_control_sale-12.0.1.0.0.99.dev7.dist-info/METADATA
odoo12_addon_project_timesheet_time_control_sale-12.0.1.0.0.99.dev7.dist-info/WHEEL
odoo12_addon_project_timesheet_time_control_sale-12.0.1.0.0.99.dev7.dist-info/top_level.txt
odoo12_addon_project_timesheet_time_control_sale-12.0.1.0.0.99.dev7.dist-info/RECORD
